{
  "levels": [
    {
      "width": 92,
      "height": 9,
      "spawn": {
        "x": 48,
        "y": 192
      },
      "exit": {
        "x": 2848,
        "y": 160
      },
      "platforms": [
        {
          "x": 0,
          "y": 7,
          "w": 92,
          "tile": 8,
          "left": 8,
          "middle": 9,
          "alt": 10,
          "right": 11
        },
        {
          "x": 0,
          "y": 8,
          "w": 92,
          "tile": 14,
          "left": 14,
          "middle": 15,
          "alt": 16,
          "right": 17
        },
        {
          "x": 6,
          "y": 5,
          "w": 8,
          "tile": 8,
          "left": 8,
          "middle": 9,
          "alt": 12,
          "right": 11
        },
        {
          "x": 17,
          "y": 5,
          "w": 7,
          "tile": 8,
          "left": 8,
          "middle": 9,
          "alt": 12,
          "right": 11
        },
        {
          "x": 28,
          "y": 4,
          "w": 8,
          "tile": 8,
          "left": 8,
          "middle": 9,
          "alt": 12,
          "right": 11
        },
        {
          "x": 40,
          "y": 5,
          "w": 8,
          "tile": 8,
          "left": 8,
          "middle": 9,
          "alt": 12,
          "right": 11
        },
        {
          "x": 52,
          "y": 4,
          "w": 7,
          "tile": 8,
          "left": 8,
          "middle": 9,
          "alt": 12,
          "right": 11
        },
        {
          "x": 63,
          "y": 5,
          "w": 8,
          "tile": 8,
          "left": 8,
          "middle": 9,
          "alt": 12,
          "right": 11
        },
        {
          "x": 74,
          "y": 4,
          "w": 8,
          "tile": 8,
          "left": 8,
          "middle": 9,
          "alt": 12,
          "right": 11
        }
      ],
      "enemies": [
        {
          "kind": 1,
          "x": 360,
          "y": 192,
          "minX": 300,
          "maxX": 520
        },
        {
          "kind": 0,
          "x": 650,
          "y": 72,
          "minX": 560,
          "maxX": 760
        },
        {
          "kind": 1,
          "x": 970,
          "y": 192,
          "minX": 860,
          "maxX": 1120
        },
        {
          "kind": 0,
          "x": 1410,
          "y": 64,
          "minX": 1260,
          "maxX": 1510
        },
        {
          "kind": 1,
          "x": 1840,
          "y": 192,
          "minX": 1720,
          "maxX": 1960
        },
        {
          "kind": 0,
          "x": 2360,
          "y": 72,
          "minX": 2240,
          "maxX": 2490
        }
      ],
      "coins": [
        {
          "x": 210,
          "y": 124
        },
        {
          "x": 258,
          "y": 124
        },
        {
          "x": 306,
          "y": 124
        },
        {
          "x": 562,
          "y": 124
        },
        {
          "x": 610,
          "y": 124
        },
        {
          "x": 658,
          "y": 124
        },
        {
          "x": 914,
          "y": 92
        },
        {
          "x": 962,
          "y": 92
        },
        {
          "x": 1010,
          "y": 92
        },
        {
          "x": 1298,
          "y": 124
        },
        {
          "x": 1346,
          "y": 124
        },
        {
          "x": 1394,
          "y": 124
        },
        {
          "x": 1682,
          "y": 92
        },
        {
          "x": 1730,
          "y": 92
        },
        {
          "x": 1778,
          "y": 92
        },
        {
          "x": 2034,
          "y": 124
        },
        {
          "x": 2082,
          "y": 124
        },
        {
          "x": 2130,
          "y": 124
        },
        {
          "x": 2386,
          "y": 92
        },
        {
          "x": 2434,
          "y": 92
        },
        {
          "x": 2482,
          "y": 92
        },
        {
          "x": 2636,
          "y": 188
        },
        {
          "x": 2760,
          "y": 188
        }
      ]
    },
    {
      "width": 112,
      "height": 9,
      "spawn": {
        "x": 48,
        "y": 192
      },
      "exit": {
        "x": 3488,
        "y": 160
      },
      "platforms": [
        {
          "x": 0,
          "y": 7,
          "w": 112,
          "tile": 18,
          "left": 18,
          "middle": 19,
          "alt": 20,
          "right": 21
        },
        {
          "x": 0,
          "y": 8,
          "w": 112,
          "tile": 14,
          "left": 14,
          "middle": 15,
          "alt": 16,
          "right": 17
        },
        {
          "x": 6,
          "y": 5,
          "w": 8,
          "tile": 18,
          "left": 18,
          "middle": 19,
          "alt": 22,
          "right": 21
        },
        {
          "x": 17,
          "y": 4,
          "w": 7,
          "tile": 18,
          "left": 18,
          "middle": 19,
          "alt": 22,
          "right": 21
        },
        {
          "x": 28,
          "y": 5,
          "w": 8,
          "tile": 18,
          "left": 18,
          "middle": 19,
          "alt": 22,
          "right": 21
        },
        {
          "x": 39,
          "y": 4,
          "w": 8,
          "tile": 18,
          "left": 18,
          "middle": 19,
          "alt": 22,
          "right": 21
        },
        {
          "x": 51,
          "y": 5,
          "w": 7,
          "tile": 18,
          "left": 18,
          "middle": 19,
          "alt": 22,
          "right": 21
        },
        {
          "x": 62,
          "y": 4,
          "w": 8,
          "tile": 18,
          "left": 18,
          "middle": 19,
          "alt": 22,
          "right": 21
        },
        {
          "x": 74,
          "y": 5,
          "w": 8,
          "tile": 18,
          "left": 18,
          "middle": 19,
          "alt": 22,
          "right": 21
        },
        {
          "x": 84,
          "y": 4,
          "w": 8,
          "tile": 18,
          "left": 18,
          "middle": 19,
          "alt": 22,
          "right": 21
        },
        {
          "x": 96,
          "y": 5,
          "w": 7,
          "tile": 18,
          "left": 18,
          "middle": 19,
          "alt": 22,
          "right": 21
        }
      ],
      "enemies": [
        {
          "kind": 1,
          "x": 380,
          "y": 192,
          "minX": 310,
          "maxX": 540
        },
        {
          "kind": 0,
          "x": 610,
          "y": 68,
          "minX": 520,
          "maxX": 760
        },
        {
          "kind": 1,
          "x": 940,
          "y": 192,
          "minX": 850,
          "maxX": 1100
        },
        {
          "kind": 0,
          "x": 1280,
          "y": 72,
          "minX": 1180,
          "maxX": 1480
        },
        {
          "kind": 1,
          "x": 1710,
          "y": 192,
          "minX": 1600,
          "maxX": 1850
        },
        {
          "kind": 0,
          "x": 2150,
          "y": 64,
          "minX": 2020,
          "maxX": 2290
        },
        {
          "kind": 1,
          "x": 2610,
          "y": 192,
          "minX": 2490,
          "maxX": 2760
        },
        {
          "kind": 0,
          "x": 3140,
          "y": 72,
          "minX": 3000,
          "maxX": 3280
        }
      ],
      "coins": [
        {
          "x": 210,
          "y": 124
        },
        {
          "x": 258,
          "y": 124
        },
        {
          "x": 306,
          "y": 124
        },
        {
          "x": 562,
          "y": 92
        },
        {
          "x": 610,
          "y": 92
        },
        {
          "x": 658,
          "y": 92
        },
        {
          "x": 914,
          "y": 124
        },
        {
          "x": 962,
          "y": 124
        },
        {
          "x": 1010,
          "y": 124
        },
        {
          "x": 1266,
          "y": 92
        },
        {
          "x": 1314,
          "y": 92
        },
        {
          "x": 1362,
          "y": 92
        },
        {
          "x": 1650,
          "y": 124
        },
        {
          "x": 1698,
          "y": 124
        },
        {
          "x": 1746,
          "y": 124
        },
        {
          "x": 2002,
          "y": 92
        },
        {
          "x": 2050,
          "y": 92
        },
        {
          "x": 2098,
          "y": 92
        },
        {
          "x": 2386,
          "y": 124
        },
        {
          "x": 2434,
          "y": 124
        },
        {
          "x": 2482,
          "y": 124
        },
        {
          "x": 2706,
          "y": 92
        },
        {
          "x": 2754,
          "y": 92
        },
        {
          "x": 2802,
          "y": 92
        },
        {
          "x": 3090,
          "y": 124
        },
        {
          "x": 3138,
          "y": 124
        },
        {
          "x": 3186,
          "y": 124
        },
        {
          "x": 3264,
          "y": 188
        },
        {
          "x": 3324,
          "y": 188
        }
      ]
    },
    {
      "width": 132,
      "height": 9,
      "spawn": {
        "x": 48,
        "y": 192
      },
      "exit": {
        "x": 4128,
        "y": 160
      },
      "platforms": [
        {
          "x": 0,
          "y": 7,
          "w": 132,
          "tile": 18,
          "left": 18,
          "middle": 19,
          "alt": 20,
          "right": 21
        },
        {
          "x": 0,
          "y": 8,
          "w": 132,
          "tile": 14,
          "left": 14,
          "middle": 15,
          "alt": 16,
          "right": 17
        },
        {
          "x": 5,
          "y": 5,
          "w": 8,
          "tile": 18,
          "left": 18,
          "middle": 19,
          "alt": 22,
          "right": 21
        },
        {
          "x": 16,
          "y": 4,
          "w": 8,
          "tile": 18,
          "left": 18,
          "middle": 19,
          "alt": 22,
          "right": 21
        },
        {
          "x": 28,
          "y": 5,
          "w": 8,
          "tile": 18,
          "left": 18,
          "middle": 19,
          "alt": 22,
          "right": 21
        },
        {
          "x": 40,
          "y": 4,
          "w": 7,
          "tile": 18,
          "left": 18,
          "middle": 19,
          "alt": 22,
          "right": 21
        },
        {
          "x": 51,
          "y": 5,
          "w": 8,
          "tile": 18,
          "left": 18,
          "middle": 19,
          "alt": 22,
          "right": 21
        },
        {
          "x": 63,
          "y": 4,
          "w": 8,
          "tile": 18,
          "left": 18,
          "middle": 19,
          "alt": 22,
          "right": 21
        },
        {
          "x": 75,
          "y": 5,
          "w": 8,
          "tile": 18,
          "left": 18,
          "middle": 19,
          "alt": 22,
          "right": 21
        },
        {
          "x": 84,
          "y": 4,
          "w": 8,
          "tile": 18,
          "left": 18,
          "middle": 19,
          "alt": 22,
          "right": 21
        },
        {
          "x": 96,
          "y": 5,
          "w": 8,
          "tile": 18,
          "left": 18,
          "middle": 19,
          "alt": 22,
          "right": 21
        },
        {
          "x": 108,
          "y": 4,
          "w": 8,
          "tile": 18,
          "left": 18,
          "middle": 19,
          "alt": 22,
          "right": 21
        }
      ],
      "enemies": [
        {
          "kind": 1,
          "x": 360,
          "y": 192,
          "minX": 300,
          "maxX": 560
        },
        {
          "kind": 0,
          "x": 610,
          "y": 68,
          "minX": 520,
          "maxX": 770
        },
        {
          "kind": 1,
          "x": 930,
          "y": 192,
          "minX": 840,
          "maxX": 1080
        },
        {
          "kind": 0,
          "x": 1280,
          "y": 62,
          "minX": 1160,
          "maxX": 1460
        },
        {
          "kind": 1,
          "x": 1660,
          "y": 192,
          "minX": 1540,
          "maxX": 1810
        },
        {
          "kind": 0,
          "x": 2060,
          "y": 72,
          "minX": 1950,
          "maxX": 2220
        },
        {
          "kind": 1,
          "x": 2520,
          "y": 192,
          "minX": 2390,
          "maxX": 2690
        },
        {
          "kind": 0,
          "x": 2940,
          "y": 64,
          "minX": 2820,
          "maxX": 3130
        },
        {
          "kind": 1,
          "x": 3420,
          "y": 192,
          "minX": 3290,
          "maxX": 3580
        },
        {
          "kind": 0,
          "x": 3820,
          "y": 72,
          "minX": 3690,
          "maxX": 3980
        }
      ],
      "coins": [
        {
          "x": 178,
          "y": 124
        },
        {
          "x": 226,
          "y": 124
        },
        {
          "x": 274,
          "y": 124
        },
        {
          "x": 530,
          "y": 92
        },
        {
          "x": 578,
          "y": 92
        },
        {
          "x": 626,
          "y": 92
        },
        {
          "x": 914,
          "y": 124
        },
        {
          "x": 962,
          "y": 124
        },
        {
          "x": 1010,
          "y": 124
        },
        {
          "x": 1298,
          "y": 92
        },
        {
          "x": 1346,
          "y": 92
        },
        {
          "x": 1394,
          "y": 92
        },
        {
          "x": 1650,
          "y": 124
        },
        {
          "x": 1698,
          "y": 124
        },
        {
          "x": 1746,
          "y": 124
        },
        {
          "x": 2034,
          "y": 92
        },
        {
          "x": 2082,
          "y": 92
        },
        {
          "x": 2130,
          "y": 92
        },
        {
          "x": 2418,
          "y": 124
        },
        {
          "x": 2466,
          "y": 124
        },
        {
          "x": 2514,
          "y": 124
        },
        {
          "x": 2706,
          "y": 92
        },
        {
          "x": 2754,
          "y": 92
        },
        {
          "x": 2802,
          "y": 92
        },
        {
          "x": 3090,
          "y": 124
        },
        {
          "x": 3138,
          "y": 124
        },
        {
          "x": 3186,
          "y": 124
        },
        {
          "x": 3474,
          "y": 92
        },
        {
          "x": 3522,
          "y": 92
        },
        {
          "x": 3570,
          "y": 92
        },
        {
          "x": 4000,
          "y": 188
        },
        {
          "x": 4060,
          "y": 188
        }
      ]
    }
  ]
}
